base_model/__init__.py
base_model/attribute_validation.py
base_model/base_model.py
base_model/base_model_exception.py
base_model/base_model_validation.py
base_model/json.py
base_model/list_base_model.py
base_model/not_found_attribute.py
base_model/tools.py
base_model_guiosoft-0.0.3.dist-info/METADATA
base_model_guiosoft-0.0.3.dist-info/WHEEL
base_model_guiosoft-0.0.3.dist-info/top_level.txt
base_model_guiosoft-0.0.3.dist-info/zip-safe
base_model_guiosoft-0.0.3.dist-info/RECORD
