Metadata-Version: 2.1
Name: base-model-guiosoft
Version: 0.0.3
Summary: Model class with attributes validation
Home-page: https://github.com/guionardo/py-base-model
Author: Guionardo Furlan
Author-email: guionardo@gmail.com
License: MIT
Project-URL: Documentation, https://github.com/guionardo/py-base-model/wiki
Project-URL: Source, https://github.com/guionardo/py-base-model
Keywords: model
Platform: UNKNOWN
Classifier: Programming Language :: Python :: 3
Classifier: License :: OSI Approved :: MIT License
Classifier: Operating System :: OS Independent
Requires-Python: >=3.6.*
Requires-Dist: python-dateutil
Requires-Dist: orjson
